definednamespace/__init__.py
generator/__init__.py
generator/generate_namespace.py
definednamespace-0.1.0.dist-info/AUTHORS
definednamespace-0.1.0.dist-info/LICENSE
definednamespace-0.1.0.dist-info/METADATA
definednamespace-0.1.0.dist-info/WHEEL
definednamespace-0.1.0.dist-info/pbr.json
definednamespace-0.1.0.dist-info/top_level.txt
definednamespace-0.1.0.dist-info/RECORD
